start_5c_daily_task/__init__.py
start_5c_daily_task/funcs_images.py
start_5c_daily_task/main.py
start_5c_daily_task-0.1.0.dist-info/entry_points.txt
start_5c_daily_task-0.1.0.dist-info/METADATA
start_5c_daily_task-0.1.0.dist-info/WHEEL
start_5c_daily_task-0.1.0.dist-info/RECORD
