Metadata-Version: 2.4
Name: start-5c-daily-task
Version: 0.1.0
Summary: 
Author: 6vi7ms
Author-email: 6vi7ms@gmail.com
Requires-Python: >=3.13
Classifier: Programming Language :: Python :: 3
Classifier: Programming Language :: Python :: 3.13
Classifier: Programming Language :: Python :: 3.14
Requires-Dist: browsercookie (>=0.8.2,<0.9.0)
Requires-Dist: pillow (>=12.0.0,<13.0.0)
Requires-Dist: pyperclip (>=1.11.0,<2.0.0)
Requires-Dist: requests (>=2.32.5,<3.0.0)
Requires-Dist: selenium (>=4.39.0,<5.0.0)
Requires-Dist: tqdm (>=4.67.1,<5.0.0)
Requires-Dist: webdriver-manager (>=4.0.2,<5.0.0)
